pyTGA/__init__.py
pyTGA/pyTGA.py
pytga-0.1.1.dist-info/licenses/LICENSE
pytga-0.1.1.dist-info/METADATA
pytga-0.1.1.dist-info/WHEEL
pytga-0.1.1.dist-info/top_level.txt
pytga-0.1.1.dist-info/RECORD
