Metadata-Version: 2.4
Name: pyTGA
Version: 0.1.1
Summary: A simple python library for parsing and processing Thermogravimetric analysis (TGA) data.
Author-email: Sebastian Rejman <s.rejman@uu.nl>
License-Expression: MIT
Project-URL: Homepage, https://github.com/MyonicS/pyTGA
Project-URL: Documentation, https://pytga.readthedocs.io
Classifier: Programming Language :: Python :: 3.9
Classifier: Programming Language :: Python :: 3.10
Classifier: Programming Language :: Python :: 3.11
Classifier: Programming Language :: Python :: 3.12
Classifier: Operating System :: OS Independent
Requires-Python: >=3.7
License-File: LICENSE
Requires-Dist: numpy
Requires-Dist: matplotlib
Requires-Dist: pandas
Requires-Dist: scipy
Requires-Dist: chardet
Requires-Dist: ipykernel
Requires-Dist: xlrd>=2.0.2
Provides-Extra: test
Requires-Dist: pytest; extra == "test"
Requires-Dist: pytest-cov; extra == "test"
Provides-Extra: dev
Requires-Dist: pytest; extra == "dev"
Requires-Dist: pytest-cov; extra == "dev"
Requires-Dist: black; extra == "dev"
Requires-Dist: flake8; extra == "dev"
Dynamic: license-file
